watermelon/__init__.py
watermelon/watermelon.py
watermelon_feature_selection-0.0.3.dist-info/LICENSE
watermelon_feature_selection-0.0.3.dist-info/METADATA
watermelon_feature_selection-0.0.3.dist-info/WHEEL
watermelon_feature_selection-0.0.3.dist-info/top_level.txt
watermelon_feature_selection-0.0.3.dist-info/RECORD
