Metadata-Version: 2.1
Name: watermelon-feature-selection
Version: 0.0.3
Summary: A python package for watermelon feature selection method
Home-page: https://github.com/Tzutori/watermelon-feature-selection
Author: Xiang Xie
Author-email: xiang.xie.china@gmail.com
License: UNKNOWN
Platform: UNKNOWN
Classifier: Programming Language :: Python :: 3.7
Classifier: License :: OSI Approved :: GNU General Public License v3 (GPLv3)
Classifier: Operating System :: Microsoft :: Windows :: Windows 10
Requires-Python: >=3.7
Requires-Dist: pandas (>=1.0.4)
Requires-Dist: numpy (>=1.18.5)
Requires-Dist: scipy (>=1.4.1)
Requires-Dist: scikit-learn (>=0.23.1)
